html5lib_truncation/__init__.py
html5lib_truncation/filters.py
html5lib_truncation/shortcuts.py
html5lib_truncation/utils.py
html5lib_truncation-0.1.0.dist-info/DESCRIPTION.rst
html5lib_truncation-0.1.0.dist-info/METADATA
html5lib_truncation-0.1.0.dist-info/metadata.json
html5lib_truncation-0.1.0.dist-info/RECORD
html5lib_truncation-0.1.0.dist-info/top_level.txt
html5lib_truncation-0.1.0.dist-info/WHEEL
tests/__init__.py
tests/conftest.py
tests/test_filters.py
tests/test_utils.py
