Metadata-Version: 1.1
Name: html5lib-truncation
Version: 0.1.0
Summary: Truncating HTML with html5lib filter
Home-page: https://github.com/tonyseek/html5lib-truncation
Author: Jiangge Zhang
Author-email: tonyseek@gmail.com
License: MIT
Platform: Any
Classifier: Development Status :: 3 - Alpha
Classifier: License :: OSI Approved :: MIT License
Classifier: Operating System :: OS Independent
Classifier: Programming Language :: Python
Classifier: Programming Language :: Python :: 2.7
Classifier: Programming Language :: Python :: 3.3
Classifier: Programming Language :: Python :: 3.4
Classifier: Programming Language :: Python :: Implementation :: PyPy
